README.txt
setup.cfg
setup.py
collective/__init__.py
collective/__init__.pyc
collective.cultureRelations.egg-info/PKG-INFO
collective.cultureRelations.egg-info/SOURCES.txt
collective.cultureRelations.egg-info/dependency_links.txt
collective.cultureRelations.egg-info/entry_points.txt
collective.cultureRelations.egg-info/namespace_packages.txt
collective.cultureRelations.egg-info/not-zip-safe
collective.cultureRelations.egg-info/paster_plugins.txt
collective.cultureRelations.egg-info/requires.txt
collective.cultureRelations.egg-info/top_level.txt
collective/cultureRelations/__init__.py
collective/cultureRelations/configure.zcml
collective/cultureRelations/overrides.zcml
collective/cultureRelations/tests.py
collective/cultureRelations/browser/__init__.py
collective/cultureRelations/browser/configure.zcml
collective/cultureRelations/browser/cultureReferences.pt
collective/cultureRelations/browser/cultureReferences.py
collective/cultureRelations/profiles/default/metadata.xml
docs/HISTORY.txt
docs/INSTALL.txt
docs/LICENSE.GPL
docs/LICENSE.txt