Metadata-Version: 1.0
Name: collective.cultureRelations
Version: 0.5
Summary: A setup for collective.viewlet.references that configures it for cultural institutions according to the INTK Online Strategy
Home-page: http://svn.plone.org/svn/collective/
Author: David Jonas
Author-email: david@itsnotthatkind.org
License: GPL
Keywords: plone setup references culture
Platform: UNKNOWN
Classifier: Framework :: Plone
Classifier: Programming Language :: Python
